fakemail.py
fakemail-0.1.0.dist-info/DESCRIPTION.rst
fakemail-0.1.0.dist-info/METADATA
fakemail-0.1.0.dist-info/RECORD
fakemail-0.1.0.dist-info/WHEEL
fakemail-0.1.0.dist-info/entry_points.txt
fakemail-0.1.0.dist-info/metadata.json
fakemail-0.1.0.dist-info/top_level.txt
