Metadata-Version: 2.0
Name: fakemail
Version: 0.1.0
Summary: A fake SMTP server
Home-page: https://ollycope.com/repos/fakemail
Author: Oliver Cope
Author-email: oliver@redgecko.org
License: Apache
Keywords: smtp http proxy
Platform: UNKNOWN
Classifier: Programming Language :: Python :: 3
Requires-Dist: aiosmtpd
Requires-Dist: aiosmtplib
Requires-Dist: aiohttp
